calibra/__init__.py
calibra/calibra.py
calibra/calibrators.py
calibra/errors.py
calibra/plotting.py
calibra/utils.py
calibra-0.3.2.dist-info/AUTHORS.rst
calibra-0.3.2.dist-info/LICENSE
calibra-0.3.2.dist-info/METADATA
calibra-0.3.2.dist-info/WHEEL
calibra-0.3.2.dist-info/top_level.txt
calibra-0.3.2.dist-info/RECORD
