Metadata-Version: 2.1
Name: calibra
Version: 0.3.2
Summary: Toolkit for calibration of machine learning classifiers.
Home-page: https://github.com/conorwalsh99/calibra
Author: Conor Walsh
Author-email: conorwalsh206@gmail.com
License: MIT license
Keywords: calibra
Classifier: Development Status :: 2 - Pre-Alpha
Classifier: Intended Audience :: Developers
Classifier: License :: OSI Approved :: MIT License
Classifier: Natural Language :: English
Classifier: Programming Language :: Python :: 3
Classifier: Programming Language :: Python :: 3.6
Classifier: Programming Language :: Python :: 3.7
Classifier: Programming Language :: Python :: 3.8
Requires-Python: >=3.6
License-File: LICENSE
License-File: AUTHORS.rst
Requires-Dist: pandas
Requires-Dist: numpy
